plotting_wand/__init__.py
plotting_wand/plotter.py
plotting_wand/helpers/__init__.py
plotting_wand/helpers/layout.py
plotting_wand/helpers/plotting.py
plotting_wand/helpers/resampling.py
plotting_wand/helpers/smoothing.py
plotting_wand/plotly/__init__.py
plotting_wand/plotly/plotter.py
plotting_wand/seaborn/__init__.py
plotting_wand/seaborn/data_processing.py
plotting_wand/seaborn/logging.py
plotting_wand/seaborn/plotter.py
plotting_wand/seaborn/post_processing.py
plotting_wand/utilities/__init__.py
plotting_wand/utilities/attributes.py
plotting_wand/utilities/data_types.py
plotting_wand/utilities/logging.py
elsa_plotting_wand-1.0.6.dist-info/LICENSE.txt
elsa_plotting_wand-1.0.6.dist-info/METADATA
elsa_plotting_wand-1.0.6.dist-info/WHEEL
elsa_plotting_wand-1.0.6.dist-info/entry_points.txt
elsa_plotting_wand-1.0.6.dist-info/top_level.txt
elsa_plotting_wand-1.0.6.dist-info/RECORD
