Metadata-Version: 2.1
Name: elsa-plotting-wand
Version: 1.0.6
Summary: Plot experimental results
Home-page: https://github.com/elsa-lab/plotting-wand
Author: Shawn Chang
Author-email: shawn420@gapp.nthu.edu.tw
License: UNKNOWN
Project-URL: Bug Reports, https://github.com/elsa-lab/plotting-wand/issues
Project-URL: Source, https://github.com/elsa-lab/plotting-wand
Keywords: data-visualization plotting plotly tool
Platform: UNKNOWN
Classifier: Development Status :: 3 - Alpha
Classifier: Intended Audience :: Developers
Classifier: Topic :: Scientific/Engineering :: Visualization
Classifier: License :: OSI Approved :: MIT License
Classifier: Programming Language :: Python :: 3
Classifier: Programming Language :: Python :: 3.5
Classifier: Programming Language :: Python :: 3.6
Classifier: Programming Language :: Python :: 3.7
Requires-Python: >=3.5, <4
Requires-Dist: matplotlib (>=3.0.0)
Requires-Dist: numpy (>=1.6.0)
Requires-Dist: pandas (>=0.13.0)
Requires-Dist: plotly (>=4.0.0)
Requires-Dist: psutil
Requires-Dist: requests
Requires-Dist: scipy (>=0.9.0)
Requires-Dist: seaborn (>=0.9.0)
Provides-Extra: dev
Requires-Dist: check-manifest ; extra == 'dev'
Provides-Extra: examples
Requires-Dist: kaggle ; extra == 'examples'
Provides-Extra: test
Requires-Dist: coverage ; extra == 'test'
